bobalkkagi/__init__.py
bobalkkagi/__main__.py
bobalkkagi/api_hook.py
bobalkkagi/application.py
bobalkkagi/constValue.py
bobalkkagi/debugger.py
bobalkkagi/dumpfiles/putty_protected_dump
bobalkkagi/globalValue.py
bobalkkagi/hookFuncs.py
bobalkkagi/kuserSharedData.py
bobalkkagi/loader.py
bobalkkagi/log/putty_protected_log.txt
bobalkkagi/logger.py
bobalkkagi/peb.py
bobalkkagi/reflector.py
bobalkkagi/teb.py
bobalkkagi/unpacking.py
bobalkkagi/unwrapping.py
bobalkkagi/util.py
bobalkkagi/util_unwrap.py
bobalkkagi-0.2.5.dist-info/entry_points.txt
bobalkkagi-0.2.5.dist-info/LICENSE
bobalkkagi-0.2.5.dist-info/METADATA
bobalkkagi-0.2.5.dist-info/WHEEL
bobalkkagi-0.2.5.dist-info/RECORD
