Metadata-Version: 2.1
Name: bobalkkagi
Version: 0.2.5
Summary: Unpack and unwrapping executables protected with Themida 3.1.x by BOB11_Bobalkkagi
License: MIT
Author: hackerhoon
Author-email: gkswlgns21@gmail.com
Requires-Python: >=3.9,<3.11
Classifier: License :: OSI Approved :: MIT License
Classifier: Programming Language :: Python :: 3
Classifier: Programming Language :: Python :: 3.9
Classifier: Programming Language :: Python :: 3.10
Requires-Dist: capstone (>=4.0.2,<5.0.0)
Requires-Dist: distorm3 (>=3.5.2,<4.0.0)
Requires-Dist: fire (>=0.4,<0.5)
Requires-Dist: lief (>=0.12.2)
Requires-Dist: pefile (>=2022.5.30,<2023.0.0)
Requires-Dist: pyinstaller (>=5.7.0,<6.0.0)
Requires-Dist: unicorn (>=2.0.1.post,<3.0.0)
